migrations/0001_initial.py
migrations/__init__.py
django_baboons_referral_0.1.6-0.1.6.dist-info/LICENSE
django_baboons_referral_0.1.6-0.1.6.dist-info/METADATA
django_baboons_referral_0.1.6-0.1.6.dist-info/WHEEL
django_baboons_referral_0.1.6-0.1.6.dist-info/top_level.txt
django_baboons_referral_0.1.6-0.1.6.dist-info/RECORD
